sam_track/__init__.py
sam_track/__main__.py
sam_track/auth.py
sam_track/cli.py
sam_track/reconciliation.py
sam_track/tracker.py
sam_track/outputs/__init__.py
sam_track/outputs/bbox.py
sam_track/outputs/seg.py
sam_track/outputs/slp.py
sam_track/prompts/__init__.py
sam_track/prompts/base.py
sam_track/prompts/pose.py
sam_track/prompts/roi.py
sam_track/prompts/text.py
sam_track-0.1.1.dist-info/METADATA
sam_track-0.1.1.dist-info/WHEEL
sam_track-0.1.1.dist-info/entry_points.txt
sam_track-0.1.1.dist-info/licenses/LICENSE
sam_track-0.1.1.dist-info/RECORD
