Metadata-Version: 2.4
Name: sam-track
Version: 0.1.1
Summary: Track objects in videos using SAM3 (Segment Anything Model 3).
Author-email: Talmo Pereira <talmo@talmolab.org>
License: BSD-3-Clause
License-File: LICENSE
Keywords: deep learning,sam3,segmentation,tracking,video
Classifier: Development Status :: 3 - Alpha
Classifier: Intended Audience :: Science/Research
Classifier: License :: OSI Approved :: BSD License
Classifier: Programming Language :: Python :: 3.12
Classifier: Programming Language :: Python :: 3.13
Classifier: Topic :: Scientific/Engineering :: Artificial Intelligence
Requires-Python: >=3.12
Requires-Dist: accelerate>=1.0.0
Requires-Dist: click>=8.1.0
Requires-Dist: h5py>=3.8.0
Requires-Dist: huggingface-hub>=0.26.0
Requires-Dist: imageio-ffmpeg>=0.5.1
Requires-Dist: imageio>=2.34.0
Requires-Dist: motmetrics>=1.4.0
Requires-Dist: numpy>=1.24.0
Requires-Dist: pyyaml>=6.0.0
Requires-Dist: rich>=13.0.0
Requires-Dist: scipy>=1.10.0
Requires-Dist: sleap-io[all]>=0.5.8
Requires-Dist: torch>=2.5.0
Requires-Dist: torchvision>=0.20.0
Requires-Dist: tqdm>=4.66.0
Requires-Dist: transformers>=5.0.0rc1
Requires-Dist: typer>=0.12.0
Provides-Extra: dev
Requires-Dist: mypy>=1.10.0; extra == 'dev'
Requires-Dist: pytest-cov>=4.0.0; extra == 'dev'
Requires-Dist: pytest>=8.0.0; extra == 'dev'
Requires-Dist: ruff>=0.5.0; extra == 'dev'
